CHANGES.txt
CONTRIBUTORS.txt
MANIFEST.in
README.rst
buildout-dev.cfg
buildout.cfg
setup.py
docs/LICENSE.txt
src/paulla/__init__.py
src/paulla.checkplanetdiff.egg-info/PKG-INFO
src/paulla.checkplanetdiff.egg-info/SOURCES.txt
src/paulla.checkplanetdiff.egg-info/dependency_links.txt
src/paulla.checkplanetdiff.egg-info/entry_points.txt
src/paulla.checkplanetdiff.egg-info/namespace_packages.txt
src/paulla.checkplanetdiff.egg-info/not-zip-safe
src/paulla.checkplanetdiff.egg-info/requires.txt
src/paulla.checkplanetdiff.egg-info/top_level.txt
src/paulla/checkplanetdiff/__init__.py
src/paulla/checkplanetdiff/check.py
src/paulla/checkplanetdiff/tests/__init__.py
src/paulla/checkplanetdiff/tests/state_critical.txt
src/paulla/checkplanetdiff/tests/state_ok.txt
src/paulla/checkplanetdiff/tests/state_warning.txt
src/paulla/checkplanetdiff/tests/test_checkplanetdiff.rst