Metadata-Version: 1.0
Name: paulla.checkplanetdiff
Version: 0.4
Summary: A nagios|icinga plugin to check diff delay with the official OpenStreetMap Planet.
Home-page: http://www.paulla.asso.fr
Author: Jean-Philippe Camguilhem
Author-email: jp.camguilhem+eggs@gmail.com
License: bsd
Keywords: Nagios Icinga OSM
Platform: any
Classifier: Programming Language :: Python
Classifier: Programming Language :: Python :: 2.7
